userlens/__init__.py
userlens/event_tracker.py
userlens/utils.py
userlens_analytics_sdk-1.0.2.dist-info/METADATA
userlens_analytics_sdk-1.0.2.dist-info/WHEEL
userlens_analytics_sdk-1.0.2.dist-info/RECORD
